yt_music_tui/__init__.py
yt_music_tui/main.py
yt_music_tui-1.0.1.dist-info/licenses/LICENSE
yt_music_tui-1.0.1.dist-info/METADATA
yt_music_tui-1.0.1.dist-info/WHEEL
yt_music_tui-1.0.1.dist-info/entry_points.txt
yt_music_tui-1.0.1.dist-info/top_level.txt
yt_music_tui-1.0.1.dist-info/RECORD
