Metadata-Version: 2.4
Name: yt-music-tui
Version: 1.0.1
Summary: A terminal-based YouTube Music player with smart filtering and smooth playback
Author: Exar1o
License: MIT
Project-URL: Homepage, https://github.com/Exar1o/yt-music-tui
Project-URL: Repository, https://github.com/Exar1o/yt-music-tui
Classifier: Programming Language :: Python :: 3
Classifier: Environment :: Console :: Curses
Classifier: Operating System :: POSIX :: Linux
Classifier: Operating System :: MacOS
Classifier: Topic :: Multimedia :: Sound/Audio :: Players
Requires-Python: >=3.7
License-File: LICENSE
Requires-Dist: yt-dlp>=2024.0.0
Dynamic: license-file
